README.rst
setup.py
rake/__init__.py
rake/custom/__init__.py
rake/custom/config/__init__.py
rake/custom/config/custom_json.py
rake/custom/config/custom_yaml.py
rake/custom/db/__init__.py
rake/custom/db/custom_mongodb.py
rake/custom/db/custom_redis.py
rake/custom/load/__init__.py
rake/workflow/__init__.py
rake/workflow/actuator.py
rake/workflow/proxy.py
rake/workflow/task.py
rake_flow.egg-info/PKG-INFO
rake_flow.egg-info/SOURCES.txt
rake_flow.egg-info/dependency_links.txt
rake_flow.egg-info/requires.txt
rake_flow.egg-info/top_level.txt