Metadata-Version: 1.0
Name: rake-flow
Version: 2.9
Summary: devops use workflow to  Batch Management System and Production Application 
Home-page: https://github.com/x0hcker/rake-flow
Author: x0hcker@gmail.com
Author-email: x0hcker@gmail.com
License: Apache Licence 2.0
Keywords: rake,paramiko,workflow,ansible
Platform: any
